macarer
tests
