Metadata-Version: 2.1
Name: macarer
Version: 1.0.2
Summary: The script created to optimize the battery charging state of the MacBook.
Home-page: https://github.com/myConsciousness/mac-battery-visitor
Author: Kato Shinya
Author-email: kato.shinya.dev@gmail.com
License: UNKNOWN
Platform: UNKNOWN
Classifier: Programming Language :: Python :: 3
Classifier: License :: OSI Approved :: Apache Software License
Classifier: Operating System :: OS Independent
Requires-Python: >=3.6
